openjiuwen/__init__.py
openjiuwen/agent/__init__.py
openjiuwen/agent/chat_agent.py
openjiuwen/agent/utils.py
openjiuwen/agent/common/__init__.py
openjiuwen/agent/common/enum.py
openjiuwen/agent/common/schema.py
openjiuwen/agent/config/__init__.py
openjiuwen/agent/config/base.py
openjiuwen/agent/config/chat_config.py
openjiuwen/agent/config/react_config.py
openjiuwen/agent/config/workflow_config.py
openjiuwen/agent/llm_agent/__init__.py
openjiuwen/agent/llm_agent/llm_agent.py
openjiuwen/agent/llm_agent/llm_controller.py
openjiuwen/agent/react_agent/__init__.py
openjiuwen/agent/react_agent/react_agent.py
openjiuwen/agent/workflow_agent/__init__.py
openjiuwen/agent/workflow_agent/workflow_agent.py
openjiuwen/agent/workflow_agent/workflow_controller.py
openjiuwen/agent_builder/__init__.py
openjiuwen/agent_builder/prompt_builder/__init__.py
openjiuwen/agent_builder/prompt_builder/base.py
openjiuwen/agent_builder/prompt_builder/builder/__init__.py
openjiuwen/agent_builder/prompt_builder/builder/badcase_prompt_builder.py
openjiuwen/agent_builder/prompt_builder/builder/feedback_prompt_builder.py
openjiuwen/agent_builder/prompt_builder/builder/meta_template_builder.py
openjiuwen/agent_builder/prompt_builder/builder/utils.py
openjiuwen/agent_builder/tune/__init__.py
openjiuwen/agent_builder/tune/base.py
openjiuwen/agent_builder/tune/utils.py
openjiuwen/agent_builder/tune/dataset/__init__.py
openjiuwen/agent_builder/tune/dataset/case_loader.py
openjiuwen/agent_builder/tune/evaluator/__init__.py
openjiuwen/agent_builder/tune/evaluator/evaluator.py
openjiuwen/agent_builder/tune/optimizer/__init__.py
openjiuwen/agent_builder/tune/optimizer/base.py
openjiuwen/agent_builder/tune/optimizer/example_optimizer.py
openjiuwen/agent_builder/tune/optimizer/instruction_optimizer.py
openjiuwen/agent_builder/tune/optimizer/joint_optimizer.py
openjiuwen/agent_builder/tune/trainer/__init__.py
openjiuwen/agent_builder/tune/trainer/base.py
openjiuwen/agent_builder/tune/trainer/trainer.py
openjiuwen-0.1.3.dist-info/LICENSE
openjiuwen-0.1.3.dist-info/METADATA
openjiuwen-0.1.3.dist-info/WHEEL
openjiuwen-0.1.3.dist-info/top_level.txt
openjiuwen-0.1.3.dist-info/RECORD
