Metadata-Version: 2.1
Name: openjiuwen
Version: 0.1.3
Summary: Add your description here
Requires-Python: >=3.11
License-File: LICENSE
Requires-Dist: aiohttp >=3.11.12
Requires-Dist: requests >=2.32.3
Requires-Dist: python-dateutil >=2.9.0.post0
Requires-Dist: filelock >=3.20.1
Requires-Dist: portalocker >=3.2.0
Requires-Dist: aiofiles >=25.1.0
Requires-Dist: sqlalchemy >=2.0.41
Requires-Dist: openai >=1.108.0
Requires-Dist: transformers >=4.52.4
Requires-Dist: tiktoken >=0.12.0
Requires-Dist: pymilvus[milvus-lite] >=2.6.2
Requires-Dist: chromadb >=1.3.7
Requires-Dist: fastmcp <3.0,>=2.14.2
Requires-Dist: docx2txt >=0.8
Requires-Dist: python-docx >=1.2.0
Requires-Dist: pdfplumber >=0.11.8
Requires-Dist: cacheout >=0.16.0
Requires-Dist: mermaid-py >=0.8.0
Requires-Dist: pycryptodome >=3.23.0
Requires-Dist: charset-normalizer >=3.4.4
Requires-Dist: pysbd >=0.3.4
